shape_creator/__init__.py
shape_creator/__main__.py
shape_creator/cli.py
shape_creator/factory.py
shape_creator/renderer.py
shape_creator/shapes.py
shape_creator/utils.py
shape_creator-1.0.0.dist-info/licenses/LICENSE
shape_creator-1.0.0.dist-info/METADATA
shape_creator-1.0.0.dist-info/WHEEL
shape_creator-1.0.0.dist-info/entry_points.txt
shape_creator-1.0.0.dist-info/top_level.txt
shape_creator-1.0.0.dist-info/RECORD
