Metadata-Version: 2.4
Name: shape-creator
Version: 1.0.0
Summary: A terminal-based 3D rotating shape renderer
Author: Oran
License: MIT License
Project-URL: Homepage, https://github.com/orancs11/Shape-Creator
Project-URL: Issues, https://github.com/orancs11/Shape-Creator/issues
Classifier: Programming Language :: Python :: 3
Classifier: License :: OSI Approved :: MIT License
Classifier: Operating System :: OS Independent
Requires-Python: >=3.6
License-File: LICENSE
Dynamic: license-file
